pokercraft_local_bankroll-0.4.0.dist-info/METADATA
pokercraft_local_bankroll-0.4.0.dist-info/WHEEL
pokercraft_local_bankroll-0.4.0.dist-info/licenses/LICENSE
pokercraft_local_bankroll/pokercraft_local_bankroll.pyi
pokercraft_local_bankroll/py.typed
pokercraft_local_bankroll/__init__.py
pokercraft_local_bankroll/pokercraft_local_bankroll.cp312-win32.pyd
pokercraft_local_bankroll-0.4.0.dist-info/RECORD
