Metadata-Version: 2.4
Name: pokercraft-local-bankroll
Version: 0.4.0
Classifier: Programming Language :: Rust
Classifier: Programming Language :: Python :: 3
Classifier: Programming Language :: Python :: Implementation :: CPython
Classifier: Topic :: Games/Entertainment :: Turn Based Strategy
Classifier: Operating System :: OS Independent
License-File: LICENSE
Keywords: poker,pokercraft,bankroll
Requires-Python: >=3.12
Project-URL: Homepage, https://github.com/McDic/pokercraft-local-bankroll
